pretty_prompt_compare/__init__.py
pretty_prompt_compare/pretty_prompt_compare.py
pretty_prompt_compare-0.0.2.dist-info/METADATA
pretty_prompt_compare-0.0.2.dist-info/WHEEL
pretty_prompt_compare-0.0.2.dist-info/licenses/LICENSE
pretty_prompt_compare-0.0.2.dist-info/RECORD
