Metadata-Version: 2.4
Name: pretty_prompt_compare
Version: 0.0.2
Summary: Compare prompts in Python with clear, pretty-printed output.
Project-URL: Homepage, https://github.com/com3dian/pretty_prompt_compare
Project-URL: Issues, https://github.com/com3dian/pretty_prompt_compare/issues
Author-email: Zehao Lu <com3dian@outlook.com>
License-File: LICENSE
Classifier: License :: OSI Approved :: MIT License
Classifier: Operating System :: OS Independent
Classifier: Programming Language :: Python :: 3
Requires-Python: >=3.10
Requires-Dist: infix
Requires-Dist: rich
